zapier/__init__.py
zapier/triggers/__init__.py
zapier/triggers/admin.py
zapier/triggers/apps.py
zapier/triggers/event.py
zapier/triggers/middleware.py
zapier/triggers/migrations/0001_initial.py
zapier/triggers/migrations/0002_triggersubscription_zap_and_more.py
zapier/triggers/migrations/0003_triggerevent_object_count_triggerevent_uuid.py
zapier/triggers/migrations/__init__.py
zapier/triggers/models/__init__.py
zapier/triggers/models/trigger_event.py
zapier/triggers/models/trigger_subscription.py
zapier/triggers/permissions.py
zapier/triggers/response.py
zapier/triggers/settings.py
zapier/triggers/types.py
zapier/triggers/urls.py
zapier/triggers/views.py
django_zapier_trigger-1.0b3.dist-info/LICENSE
django_zapier_trigger-1.0b3.dist-info/WHEEL
django_zapier_trigger-1.0b3.dist-info/METADATA
django_zapier_trigger-1.0b3.dist-info/RECORD
