Metadata-Version: 2.1
Name: django-zapier-trigger
Version: 1.0b3
Summary: Django (DRF) backed app for managing Zapier triggers.
Home-page: https://github.com/yunojuno/django-zapier-trigger
License: MIT
Author: YunoJuno
Author-email: code@yunojuno.com
Maintainer: YunoJuno
Maintainer-email: code@yunojuno.com
Requires-Python: >=3.10,<4.0
Classifier: Development Status :: 3 - Alpha
Classifier: Environment :: Web Environment
Classifier: Framework :: Django
Classifier: Framework :: Django :: 3.2
Classifier: Framework :: Django :: 4.0
Classifier: Framework :: Django :: 4.1
Classifier: License :: OSI Approved :: MIT License
Classifier: Operating System :: OS Independent
Classifier: Programming Language :: Python :: 3
Classifier: Programming Language :: Python :: 3 :: Only
Classifier: Programming Language :: Python :: 3.10
Requires-Dist: django (>=3.2,<5.0)
Requires-Dist: djangorestframework
Requires-Dist: python-dateutil
Requires-Dist: pytz
Requires-Dist: requests
Project-URL: Documentation, https://github.com/yunojuno/django-zapier-trigger
Project-URL: Repository, https://github.com/yunojuno/django-zapier-trigger
